azionpy/__init__.py
azionpy/api_auth.py
azionpy/client.py
azionpy/exceptions/__init__.py
azionpy/exceptions/azion_exceptions.py
azionpy/models.py
azionpy-0.1.1.dist-info/METADATA
azionpy-0.1.1.dist-info/WHEEL
azionpy-0.1.1.dist-info/RECORD
