Metadata-Version: 2.1
Name: azionpy
Version: 0.1.1
Summary: Um pacote simples para interagir com a API da Azion e seus serviços.
Home-page: https://azionpy.freire.live/
Author: Cesar Freire
Author-email: cesar.freire@magazord.com.br
Requires-Python: >=3.10,<4.0
Classifier: Programming Language :: Python :: 3
Classifier: Programming Language :: Python :: 3.10
Classifier: Programming Language :: Python :: 3.11
Requires-Dist: httpx (>=0.25.0,<0.26.0)
Requires-Dist: pydantic (>=2.4.2,<3.0.0)
Project-URL: Documentation, https://azionpy.freire.live/
Project-URL: Repository, https://github.com/cesarmagazord/azionpy
